flask_uxfab/__init__.py
flask_uxfab/utils.py
flask_uxfab/wizardry.py
flask_uxfab/templates/uxfab/form.html
flask_uxfab/templates/uxfab/form_autocomplete.html
flask_uxfab/templates/uxfab/formplus.html
flask_uxfab/templates/uxfab/wtf.html
Flask_UXFab-0.0.1.dist-info/LICENSE
Flask_UXFab-0.0.1.dist-info/METADATA
Flask_UXFab-0.0.1.dist-info/WHEEL
Flask_UXFab-0.0.1.dist-info/top_level.txt
Flask_UXFab-0.0.1.dist-info/RECORD
