Metadata-Version: 2.1
Name: Flask-UXFab
Version: 0.0.1
License-File: LICENSE
Requires-Dist: Flask-WTF
Requires-Dist: Flask-SQLAlchemy
Requires-Dist: Flask-FEFset
